LICENSE
bigledger_pytwin/__init__.py
bigledger_pytwin/hello_world.py
bigledger_pytwin-0.1.0.dist-info/LICENSE
bigledger_pytwin-0.1.0.dist-info/WHEEL
bigledger_pytwin-0.1.0.dist-info/entry_points.txt
bigledger_pytwin-0.1.0.dist-info/METADATA
bigledger_pytwin-0.1.0.dist-info/RECORD
