Metadata-Version: 2.1
Name: bigledger-pytwin
Version: 0.1.0
Summary: PythonBot Twin Framework
Home-page: https://bigledger.com
Keywords: digital twin,python bot
Author: Vincent Lee
Author-email: vincent@akaun.com
Requires-Python: >=3.9,<4.0
Classifier: Development Status :: 1 - Planning
Classifier: Environment :: Console
Classifier: Framework :: Flask
Classifier: License :: Other/Proprietary License
Classifier: Operating System :: OS Independent
Classifier: Programming Language :: Python :: 3
Classifier: Programming Language :: Python :: 3.9
Classifier: Programming Language :: Python :: 3.10
Classifier: Programming Language :: Python :: 3.11
Classifier: Topic :: Software Development :: Libraries :: Python Modules
Requires-Dist: twine (>=4.0.2,<5.0.0)
Project-URL: Repository, https://github.com/pythonbot-com/ptb-twin-framework
